[
  {
    "Index": 1,
    "Start Time": "00:00:00,000",
    "End Time": "00:00:02,160",
    "Speaker": "SPEAKER_02",
    "Text": "You got to be out of your mind, Jack."
  },
  {
    "Index": 2,
    "Start Time": "00:00:03,360",
    "End Time": "00:00:05,340",
    "Speaker": "SPEAKER_02",
    "Text": "You really scared a shit out of me."
  },
  {
    "Index": 3,
    "Start Time": "00:00:05,840",
    "End Time": "00:00:07,080",
    "Speaker": "SPEAKER_02",
    "Text": "Now, I'll see you in a few minutes."
  },
  {
    "Index": 4,
    "Start Time": "00:00:08,880",
    "End Time": "00:00:11,500",
    "Speaker": "SPEAKER_02",
    "Text": "I don't give a shit if you want to get tough or not, buddy."
  },
  {
    "Index": 5,
    "Start Time": "00:00:11,560",
    "End Time": "00:00:12,760",
    "Speaker": "SPEAKER_02",
    "Text": "I'll twist your head off."
  },
  {
    "Index": 6,
    "Start Time": "00:00:13,720",
    "End Time": "00:00:14,700",
    "Speaker": "SPEAKER_02",
    "Text": "You're just talking shit."
  },
  {
    "Index": 7,
    "Start Time": "00:00:14,800",
    "End Time": "00:00:16,680",
    "Speaker": "SPEAKER_02",
    "Text": "I don't believe you brave enough to come down here now."
  },
  {
    "Index": 8,
    "Start Time": "00:00:16,880",
    "End Time": "00:00:17,420",
    "Speaker": "SPEAKER_02",
    "Text": "Let's go."
  },
  {
    "Index": 9,
    "Start Time": "00:00:18,120",
    "End Time": "00:00:18,960",
    "Speaker": "SPEAKER_02",
    "Text": "Let's go, buddy."
  },
  {
    "Index": 10,
    "Start Time": "00:00:19,020",
    "End Time": "00:00:20,060",
    "Speaker": "SPEAKER_01",
    "Text": "I ain't done this in a while."
  },
  {
    "Index": 11,
    "Start Time": "00:00:20,140",
    "End Time": "00:00:20,820",
    "Speaker": "SPEAKER_01",
    "Text": "I'll enjoy it."
  },
  {
    "Index": 12,
    "Start Time": "00:00:21,120",
    "End Time": "00:00:23,200",
    "Speaker": "SPEAKER_01",
    "Text": "I could tell you, Trachia, if you wanted it,"
  },
  {
    "Index": 13,
    "Start Time": "00:00:23,200",
    "End Time": "00:00:24,900",
    "Speaker": "SPEAKER_01",
    "Text": "but that's about as close as I could do."
  },
  {
    "Index": 14,
    "Start Time": "00:00:25,620",
    "End Time": "00:00:26,240",
    "Speaker": "SPEAKER_01",
    "Text": "What, pal?"
  },
  {
    "Index": 15,
    "Start Time": "00:00:27,040",
    "End Time": "00:00:29,760",
    "Speaker": "SPEAKER_00",
    "Text": "You ain't getting in love with me, but this is my property,"
  },
  {
    "Index": 16,
    "Start Time": "00:00:30,000",
    "End Time": "00:00:32,640",
    "Speaker": "SPEAKER_00",
    "Text": "You get the hell off of it and stay off of it."
  },
  {
    "Index": 17,
    "Start Time": "00:00:33,600",
    "End Time": "00:00:35,080",
    "Speaker": "SPEAKER_00",
    "Text": "A home potion."
  },
  {
    "Index": 18,
    "Start Time": "00:00:35,620",
    "End Time": "00:00:38,720",
    "Speaker": "SPEAKER_00",
    "Text": "It's the grossest thing I've ever faced my whole life."
  },
  {
    "Index": 19,
    "Start Time": "00:00:39,900",
    "End Time": "00:00:40,820",
    "Speaker": "SPEAKER_00",
    "Text": "Buzzy old monkey."
  }
]